dependo/__init__.py
dependo/decorators.py
dependo/exceptions.py
dependo/injectable.py
dependo/lifetime.py
dependo/py.typed
dependo/service_collection.py
dependo/service_descriptor.py
dependo/service_provider.py
dependo/service_scope.py
dependo-1.1.0.dist-info/METADATA
dependo-1.1.0.dist-info/WHEEL
dependo-1.1.0.dist-info/licenses/LICENSE
dependo-1.1.0.dist-info/RECORD
