Metadata-Version: 2.4
Name: dependo
Version: 1.1.0
Summary: A lightweight, fully-typed dependency injection framework for Python 3.10+ providing scoped, transient, and singleton lifetimes.
License: MIT License
License-File: LICENSE
Keywords: dependency-injection,di,python,ioc,framework
Author: MightGainer
Author-email: yukyitchow@gmail.com
Requires-Python: >=3.10
Classifier: Development Status :: 4 - Beta
Classifier: Intended Audience :: Developers
Classifier: License :: OSI Approved :: MIT License
Classifier: Programming Language :: Python :: 3.10
Classifier: Programming Language :: Python :: 3.11
Classifier: Programming Language :: Python :: 3.12
Classifier: Topic :: Software Development :: Libraries
Classifier: Typing :: Typed
